src/__init__.py
src/server.py
src/core/__init__.py
src/core/operation_log.py
src/core/pattern_parser.py
src/core/renamer.py
src/tools/__init__.py
src/tools/batch_rename.py
src/tools/scan_files.py
src/tools/undo_rename.py
src/utils/__init__.py
src/utils/config_loader.py
src/utils/paths.py
src/utils/security.py
batch_rename_mcp-1.0.2.dist-info/METADATA
batch_rename_mcp-1.0.2.dist-info/WHEEL
batch_rename_mcp-1.0.2.dist-info/entry_points.txt
batch_rename_mcp-1.0.2.dist-info/RECORD
